euc2mqtt/CLI.py
euc2mqtt/EatonAPI.py
euc2mqtt/HassioAPI.py
euc2mqtt/InteropE2H.py
euc2mqtt/Utility.py
euc2mqtt/__init__.py
euc2mqtt/__main__.py
euc2mqtt-1.0.0.dist-info/LICENSE
euc2mqtt-1.0.0.dist-info/METADATA
euc2mqtt-1.0.0.dist-info/WHEEL
euc2mqtt-1.0.0.dist-info/entry_points.txt
euc2mqtt-1.0.0.dist-info/top_level.txt
euc2mqtt-1.0.0.dist-info/RECORD
