Metadata-Version: 2.1
Name: euc2mqtt
Version: 1.0.0
Summary: Eaton UPS Companion to MQTT Publisher
Author: islandc_
License: MIT License
Project-URL: Repository, https://github.com/islandcontroller/euc2mqtt.git
Project-URL: Issues, https://github.com/islandcontroller/euc2mqtt/issues/
Project-URL: Documentation, https://github.com/islandcontroller/euc2mqtt?tab=readme-ov-file
Keywords: eaton,ups,mqtt
Classifier: Development Status :: 3 - Alpha
Classifier: License :: OSI Approved :: MIT License
Classifier: Operating System :: OS Independent
Classifier: Programming Language :: Python :: 3
Classifier: Programming Language :: Python :: 3.12
Classifier: Topic :: Communications
Requires-Python: >=3.12
License-File: LICENSE
Requires-Dist: paho-mqtt >=2.0.0
Requires-Dist: requests >=2.31.0
Provides-Extra: test
Requires-Dist: pytest >=8.1 ; extra == 'test'
Requires-Dist: pytest-cov >=4.1 ; extra == 'test'
Requires-Dist: responses >=0.25 ; extra == 'test'
Requires-Dist: ruff >=0.3 ; extra == 'test'
